whylabs_toolkit/__init__.py
whylabs_toolkit/container/config_types.py
whylabs_toolkit/helpers/__init__.py
whylabs_toolkit/helpers/client.py
whylabs_toolkit/helpers/config.py
whylabs_toolkit/helpers/cron_validators.py
whylabs_toolkit/helpers/dataset_profiles.py
whylabs_toolkit/helpers/models.py
whylabs_toolkit/helpers/monitor_helpers.py
whylabs_toolkit/helpers/schema.py
whylabs_toolkit/helpers/utils.py
whylabs_toolkit/monitor/__init__.py
whylabs_toolkit/monitor/diagnoser/__init__.py
whylabs_toolkit/monitor/diagnoser/constants.py
whylabs_toolkit/monitor/diagnoser/converters/__init__.py
whylabs_toolkit/monitor/diagnoser/converters/granularity.py
whylabs_toolkit/monitor/diagnoser/helpers/__init__.py
whylabs_toolkit/monitor/diagnoser/helpers/describe.py
whylabs_toolkit/monitor/diagnoser/helpers/utils.py
whylabs_toolkit/monitor/diagnoser/models/__init__.py
whylabs_toolkit/monitor/diagnoser/models/diagnosis_report.py
whylabs_toolkit/monitor/diagnoser/models/noisy_monitors.py
whylabs_toolkit/monitor/diagnoser/monitor_diagnoser.py
whylabs_toolkit/monitor/diagnoser/recommendation/__init__.py
whylabs_toolkit/monitor/diagnoser/recommendation/change_recommender.py
whylabs_toolkit/monitor/diagnoser/recommendation/manual_change.py
whylabs_toolkit/monitor/diagnoser/recommendation/recommended_change.py
whylabs_toolkit/monitor/diagnoser/recommendation/remove_columns.py
whylabs_toolkit/monitor/diagnoser/targeting.py
whylabs_toolkit/monitor/manager/__init__.py
whylabs_toolkit/monitor/manager/credentials.py
whylabs_toolkit/monitor/manager/manager.py
whylabs_toolkit/monitor/manager/monitor_setup.py
whylabs_toolkit/monitor/models/__init__.py
whylabs_toolkit/monitor/models/analyzer/__init__.py
whylabs_toolkit/monitor/models/analyzer/algorithms.py
whylabs_toolkit/monitor/models/analyzer/analyzer.py
whylabs_toolkit/monitor/models/analyzer/baseline.py
whylabs_toolkit/monitor/models/analyzer/targets.py
whylabs_toolkit/monitor/models/column_schema.py
whylabs_toolkit/monitor/models/commons.py
whylabs_toolkit-0.1.2.dist-info/LICENSE
whylabs_toolkit-0.1.2.dist-info/WHEEL
whylabs_toolkit-0.1.2.dist-info/METADATA
whylabs_toolkit-0.1.2.dist-info/RECORD
