Metadata-Version: 2.1
Name: whylabs-toolkit
Version: 0.1.2
Summary: Whylabs Toolkit package.
License: Apache-2.0 license
Author: Murilo Mendonca
Author-email: murilommen@gmail.com
Requires-Python: >=3.8,<4.0
Classifier: License :: Other/Proprietary License
Classifier: Programming Language :: Python :: 3
Classifier: Programming Language :: Python :: 3.8
Classifier: Programming Language :: Python :: 3.9
Classifier: Programming Language :: Python :: 3.10
Classifier: Programming Language :: Python :: 3.11
Provides-Extra: diagnoser
Requires-Dist: isodate (>=0.6.1,<0.7.0); extra == "diagnoser"
Requires-Dist: jsonschema (>=4.17.3,<5.0.0)
Requires-Dist: numpy (>=1.24.1,<2.0.0); extra == "diagnoser"
Requires-Dist: pandas (>=2.0.3,<3.0.0); extra == "diagnoser"
Requires-Dist: pydantic (>=1.10.15,<2.0.0)
Requires-Dist: python-dateutil (>=2.8.2,<3.0.0); extra == "diagnoser"
Requires-Dist: tabulate (>=0.8.9,<0.9.0); extra == "diagnoser"
Requires-Dist: typing-extensions (>=4.11.0,<5.0.0)
Requires-Dist: urllib3 (>=2.0.2,<2.1)
Requires-Dist: whylabs-client (>=0.6.3,<0.7.0)
Requires-Dist: whylogs (>=1.1.26,<2.0.0)
